addtobuildlist/__init__.py
addtobuildlist/addtobuildlist.py
addtobuildlist-0.4.dist-info/DESCRIPTION.rst
addtobuildlist-0.4.dist-info/METADATA
addtobuildlist-0.4.dist-info/RECORD
addtobuildlist-0.4.dist-info/WHEEL
addtobuildlist-0.4.dist-info/metadata.json
addtobuildlist-0.4.dist-info/top_level.txt
