Metadata-Version: 2.0
Name: addtobuildlist
Version: 0.4
Summary: Print on output and on a unique log file 
Home-page: https://github.com/Tibibv/addtobuildlist
Author: Kron
Author-email: kron_bv@yahoo.com
License: MIT
Platform: UNKNOWN
Requires-Dist: printandlog
